khulnasoft_analyze_cli/__init__.py
khulnasoft_analyze_cli/cli.py
khulnasoft_analyze_cli/commands.py
khulnasoft_analyze_cli/config.py
khulnasoft_analyze_cli/key_store.py
khulnasoft_analyze_cli/utilities.py
khulnasoft_analyze_cli-1.11.dist-info/LICENSE
khulnasoft_analyze_cli-1.11.dist-info/METADATA
khulnasoft_analyze_cli-1.11.dist-info/WHEEL
khulnasoft_analyze_cli-1.11.dist-info/entry_points.txt
khulnasoft_analyze_cli-1.11.dist-info/top_level.txt
khulnasoft_analyze_cli-1.11.dist-info/RECORD
