Metadata-Version: 2.1
Name: khulnasoft-analyze-cli
Version: 1.11
Summary: Client library for Khulnasoft cloud service
Author: Khulnasoft Labs ltd.
License: Apache License v2
Keywords: khulnasoft
Classifier: Programming Language :: Python :: 3.8
Classifier: Programming Language :: Python :: 3.9
Classifier: Programming Language :: Python :: 3.10
Classifier: Programming Language :: Python :: 3.11
Classifier: Programming Language :: Python :: 3.12
Requires-Python: >=3.8
License-File: LICENSE
Requires-Dist: click ==7.1.2
Requires-Dist: khulnasoft-analyze-sdk <2,>=1.15.2
